{
  "authors": [
    {
      "author": "nicola-betts"
    }
  ],
  "showOnPodcast": true,
  "itunesImage": "/uploads/logo.jpg",
  "colour": "green",
  "date": "2015-06-14T12:00:00+01:00",
  "audioFile": "https://s3-eu-west-1.amazonaws.com/gatewaychurchyork/20150614.mp3",
  "subtitle": "Paul and Nicola Betts teach from Paul's instructions to children and parents.",
  "title": "Children and parents",
  "image": "/uploads/Ephesians.jpg",
  "podcastFile": "https://s3-eu-west-1.amazonaws.com/gatewaychurchyork/20150614.mp3",
  "contentLength": "21097651",
  "contentType": "audio/mp3",
  "duration": 2637.072
}