{
  "authors": [
    {
      "author": "caleb-ellwood"
    }
  ],
  "showOnPodcast": true,
  "itunesImage": "/uploads/logo.jpg",
  "deck": "Caleb continues our Kingdom Living series as he looks at Jesus' comments on giving in Matthew 6",
  "colour": "green",
  "date": "2017-04-23T12:00:00+01:00",
  "audioFile": "https://s3-eu-west-1.amazonaws.com/gatewaychurchyork/170423%2520Caleb%2520Ellwood.mp3",
  "subtitle": "Caleb continues our Kingdom Living series as he looks at Jesus' comments on giving in Matthew 6",
  "title": "Giving: to perform or to please God? ",
  "image": "/uploads/Kingdom Living.jpg"
}