{
  "authors": [
    {
      "author": "caleb-ellwood"
    }
  ],
  "showOnPodcast": true,
  "itunesImage": "/uploads/logo.jpg",
  "colour": "green",
  "date": "2018-10-28T12:00:00+00:00",
  "audioFile": "https://s3-eu-west-1.amazonaws.com/gatewaychurchyork/uploads/20181028%20Bryan%20Stevenson%20(GLS)%20-%20Caleb%20intro.mp3",
  "subtitle": "Caleb introduces a talk by Bryan Stevenson, Founder and Executive Director of the Equal Justice Initiative. If you would like to view the full talk, please contact the office. ",
  "title": "Justice",
  "image": "/uploads/Compassion & Justice.jpg"
}